{
  "page": 467,
  "coords": {
    "39:75:1": {
      "h": {
        "x": 789,
        "y": 22,
        "w": 87,
        "h": 68
      },
      "p": {
        "x": 789,
        "y": 17,
        "w": 87,
        "h": 23
      },
      "o": {
        "x": 0,
        "y": 22,
        "w": 39,
        "h": 68
      }
    },
    "39:75:2": {
      "h": {
        "x": 624,
        "y": 22,
        "w": 165,
        "h": 68
      },
      "p": {
        "x": 624,
        "y": 17,
        "w": 165,
        "h": 23
      },
      "o": {
        "x": 0,
        "y": 22,
        "w": 39,
        "h": 68
      }
    },
    "39:75:3": {
      "h": {
        "x": 473,
        "y": 22,
        "w": 151,
        "h": 68
      },
      "p": {
        "x": 473,
        "y": 17,
        "w": 151,
        "h": 23
      },
      "o": {
        "x": 0,
        "y": 22,
        "w": 39,
        "h": 68
      }
    },
    "39:75:4": {
      "h": {
        "x": 439,
        "y": 22,
        "w": 34,
        "h": 68
      },
      "p": {
        "x": 439,
        "y": 17,
        "w": 34,
        "h": 23
      },
      "o": {
        "x": 0,
        "y": 22,
        "w": 39,
        "h": 68
      }
    },
    "39:75:5": {
      "h": {
        "x": 361,
        "y": 22,
        "w": 78,
        "h": 68
      },
      "p": {
        "x": 361,
        "y": 17,
        "w": 78,
        "h": 23
      },
      "o": {
        "x": 0,
        "y": 22,
        "w": 39,
        "h": 68
      }
    },
    "39:75:6": {
      "h": {
        "x": 238,
        "y": 22,
        "w": 123,
        "h": 68
      },
      "p": {
        "x": 238,
        "y": 17,
        "w": 123,
        "h": 23
      },
      "o": {
        "x": 0,
        "y": 22,
        "w": 39,
        "h": 68
      }
    },
    "39:75:7": {
      "h": {
        "x": 121,
        "y": 22,
        "w": 117,
        "h": 68
      },
      "p": {
        "x": 121,
        "y": 17,
        "w": 117,
        "h": 23
      },
      "o": {
        "x": 0,
        "y": 22,
        "w": 39,
        "h": 68
      }
    },
    "39:75:8": {
      "h": {
        "x": 40,
        "y": 22,
        "w": 81,
        "h": 68
      },
      "p": {
        "x": 40,
        "y": 17,
        "w": 81,
        "h": 23
      },
      "o": {
        "x": 0,
        "y": 22,
        "w": 39,
        "h": 68
      }
    },
    "39:75:9": {
      "h": {
        "x": 797,
        "y": 113,
        "w": 81,
        "h": 68
      },
      "p": {
        "x": 797,
        "y": 108,
        "w": 81,
        "h": 23
      },
      "o": {
        "x": 0,
        "y": 113,
        "w": 39,
        "h": 68
      }
    },
    "39:75:11": {
      "h": {
        "x": 686,
        "y": 113,
        "w": 110,
        "h": 68
      },
      "p": {
        "x": 686,
        "y": 108,
        "w": 110,
        "h": 23
      },
      "o": {
        "x": 0,
        "y": 113,
        "w": 39,
        "h": 68
      }
    },
    "39:75:12": {
      "h": {
        "x": 596,
        "y": 113,
        "w": 90,
        "h": 68
      },
      "p": {
        "x": 596,
        "y": 108,
        "w": 90,
        "h": 23
      },
      "o": {
        "x": 0,
        "y": 113,
        "w": 39,
        "h": 68
      }
    },
    "39:75:13": {
      "h": {
        "x": 503,
        "y": 113,
        "w": 93,
        "h": 68
      },
      "p": {
        "x": 503,
        "y": 108,
        "w": 93,
        "h": 23
      },
      "o": {
        "x": 0,
        "y": 113,
        "w": 39,
        "h": 68
      }
    },
    "39:75:14": {
      "h": {
        "x": 434,
        "y": 113,
        "w": 69,
        "h": 68
      },
      "p": {
        "x": 434,
        "y": 108,
        "w": 69,
        "h": 23
      },
      "o": {
        "x": 0,
        "y": 113,
        "w": 39,
        "h": 68
      }
    },
    "39:75:15": {
      "h": {
        "x": 334,
        "y": 113,
        "w": 100,
        "h": 68
      },
      "p": {
        "x": 334,
        "y": 108,
        "w": 100,
        "h": 23
      },
      "o": {
        "x": 0,
        "y": 113,
        "w": 39,
        "h": 68
      }
    },
    "39:75:16": {
      "h": {
        "x": 287,
        "y": 113,
        "w": 47,
        "h": 68
      },
      "p": {
        "x": 287,
        "y": 108,
        "w": 47,
        "h": 23
      },
      "o": {
        "x": 0,
        "y": 113,
        "w": 39,
        "h": 68
      }
    },
    "39:75:17": {
      "h": {
        "x": 204,
        "y": 113,
        "w": 83,
        "h": 68
      },
      "p": {
        "x": 204,
        "y": 108,
        "w": 83,
        "h": 23
      },
      "o": {
        "x": 0,
        "y": 113,
        "w": 39,
        "h": 68
      }
    },
    "39:75:18": {
      "h": {
        "x": 115,
        "y": 113,
        "w": 89,
        "h": 68
      },
      "p": {
        "x": 115,
        "y": 108,
        "w": 89,
        "h": 23
      },
      "o": {
        "x": 0,
        "y": 113,
        "w": 39,
        "h": 68
      }
    },
    "40:1:1": {
      "h": {
        "x": 800,
        "y": 394,
        "w": 70,
        "h": 68
      },
      "p": {
        "x": 800,
        "y": 389,
        "w": 70,
        "h": 23
      },
      "o": {
        "x": 0,
        "y": 394,
        "w": 39,
        "h": 68
      }
    },
    "40:2:1": {
      "h": {
        "x": 627,
        "y": 394,
        "w": 101,
        "h": 68
      },
      "p": {
        "x": 627,
        "y": 389,
        "w": 101,
        "h": 23
      },
      "o": {
        "x": 0,
        "y": 394,
        "w": 39,
        "h": 68
      }
    },
    "40:2:2": {
      "h": {
        "x": 486,
        "y": 394,
        "w": 141,
        "h": 68
      },
      "p": {
        "x": 486,
        "y": 389,
        "w": 141,
        "h": 23
      },
      "o": {
        "x": 0,
        "y": 394,
        "w": 39,
        "h": 68
      }
    },
    "40:2:3": {
      "h": {
        "x": 422,
        "y": 394,
        "w": 64,
        "h": 68
      },
      "p": {
        "x": 422,
        "y": 389,
        "w": 64,
        "h": 23
      },
      "o": {
        "x": 0,
        "y": 394,
        "w": 39,
        "h": 68
      }
    },
    "40:2:4": {
      "h": {
        "x": 377,
        "y": 394,
        "w": 45,
        "h": 68
      },
      "p": {
        "x": 377,
        "y": 389,
        "w": 45,
        "h": 23
      },
      "o": {
        "x": 0,
        "y": 394,
        "w": 39,
        "h": 68
      }
    },
    "40:2:5": {
      "h": {
        "x": 289,
        "y": 394,
        "w": 88,
        "h": 68
      },
      "p": {
        "x": 289,
        "y": 389,
        "w": 88,
        "h": 23
      },
      "o": {
        "x": 0,
        "y": 394,
        "w": 39,
        "h": 68
      }
    },
    "40:2:6": {
      "h": {
        "x": 168,
        "y": 394,
        "w": 121,
        "h": 68
      },
      "p": {
        "x": 168,
        "y": 389,
        "w": 121,
        "h": 23
      },
      "o": {
        "x": 0,
        "y": 394,
        "w": 39,
        "h": 68
      }
    },
    "40:3:1": {
      "h": {
        "x": 40,
        "y": 394,
        "w": 55,
        "h": 68
      },
      "p": {
        "x": 40,
        "y": 389,
        "w": 55,
        "h": 23
      },
      "o": {
        "x": 0,
        "y": 394,
        "w": 39,
        "h": 68
      }
    },
    "40:3:2": {
      "h": {
        "x": 775,
        "y": 488,
        "w": 104,
        "h": 68
      },
      "p": {
        "x": 775,
        "y": 483,
        "w": 104,
        "h": 23
      },
      "o": {
        "x": 0,
        "y": 488,
        "w": 39,
        "h": 68
      }
    },
    "40:3:3": {
      "h": {
        "x": 668,
        "y": 488,
        "w": 107,
        "h": 68
      },
      "p": {
        "x": 668,
        "y": 483,
        "w": 107,
        "h": 23
      },
      "o": {
        "x": 0,
        "y": 488,
        "w": 39,
        "h": 68
      }
    },
    "40:3:4": {
      "h": {
        "x": 580,
        "y": 488,
        "w": 88,
        "h": 68
      },
      "p": {
        "x": 580,
        "y": 483,
        "w": 88,
        "h": 23
      },
      "o": {
        "x": 0,
        "y": 488,
        "w": 39,
        "h": 68
      }
    },
    "40:3:5": {
      "h": {
        "x": 515,
        "y": 488,
        "w": 65,
        "h": 68
      },
      "p": {
        "x": 515,
        "y": 483,
        "w": 65,
        "h": 23
      },
      "o": {
        "x": 0,
        "y": 488,
        "w": 39,
        "h": 68
      }
    },
    "40:3:6": {
      "h": {
        "x": 352,
        "y": 488,
        "w": 163,
        "h": 68
      },
      "p": {
        "x": 352,
        "y": 483,
        "w": 163,
        "h": 23
      },
      "o": {
        "x": 0,
        "y": 488,
        "w": 39,
        "h": 68
      }
    },
    "40:3:7": {
      "h": {
        "x": 329,
        "y": 488,
        "w": 23,
        "h": 68
      },
      "p": {
        "x": 329,
        "y": 483,
        "w": 23,
        "h": 23
      },
      "o": {
        "x": 0,
        "y": 488,
        "w": 39,
        "h": 68
      }
    },
    "40:3:8": {
      "h": {
        "x": 221,
        "y": 488,
        "w": 108,
        "h": 68
      },
      "p": {
        "x": 221,
        "y": 483,
        "w": 108,
        "h": 23
      },
      "o": {
        "x": 0,
        "y": 488,
        "w": 39,
        "h": 68
      }
    },
    "40:3:10": {
      "h": {
        "x": 178,
        "y": 488,
        "w": 41,
        "h": 68
      },
      "p": {
        "x": 178,
        "y": 483,
        "w": 41,
        "h": 23
      },
      "o": {
        "x": 0,
        "y": 488,
        "w": 39,
        "h": 68
      }
    },
    "40:3:11": {
      "h": {
        "x": 134,
        "y": 488,
        "w": 44,
        "h": 68
      },
      "p": {
        "x": 134,
        "y": 483,
        "w": 44,
        "h": 23
      },
      "o": {
        "x": 0,
        "y": 488,
        "w": 39,
        "h": 68
      }
    },
    "40:3:12": {
      "h": {
        "x": 79,
        "y": 488,
        "w": 55,
        "h": 68
      },
      "p": {
        "x": 79,
        "y": 483,
        "w": 55,
        "h": 23
      },
      "o": {
        "x": 0,
        "y": 488,
        "w": 39,
        "h": 68
      }
    },
    "40:3:13": {
      "h": {
        "x": 43,
        "y": 488,
        "w": 36,
        "h": 68
      },
      "p": {
        "x": 43,
        "y": 483,
        "w": 36,
        "h": 23
      },
      "o": {
        "x": 0,
        "y": 488,
        "w": 39,
        "h": 68
      }
    },
    "40:3:15": {
      "h": {
        "x": 793,
        "y": 582,
        "w": 86,
        "h": 68
      },
      "p": {
        "x": 793,
        "y": 577,
        "w": 86,
        "h": 23
      },
      "o": {
        "x": 0,
        "y": 582,
        "w": 39,
        "h": 68
      }
    },
    "40:3:16": {
      "h": {
        "x": 669,
        "y": 582,
        "w": 124,
        "h": 68
      },
      "p": {
        "x": 669,
        "y": 577,
        "w": 124,
        "h": 23
      },
      "o": {
        "x": 0,
        "y": 582,
        "w": 39,
        "h": 68
      }
    },
    "40:4:1": {
      "h": {
        "x": 566,
        "y": 582,
        "w": 30,
        "h": 68
      },
      "p": {
        "x": 566,
        "y": 577,
        "w": 30,
        "h": 23
      },
      "o": {
        "x": 0,
        "y": 582,
        "w": 39,
        "h": 68
      }
    },
    "40:4:2": {
      "h": {
        "x": 448,
        "y": 582,
        "w": 118,
        "h": 68
      },
      "p": {
        "x": 448,
        "y": 577,
        "w": 118,
        "h": 23
      },
      "o": {
        "x": 0,
        "y": 582,
        "w": 39,
        "h": 68
      }
    },
    "40:4:3": {
      "h": {
        "x": 416,
        "y": 582,
        "w": 32,
        "h": 68
      },
      "p": {
        "x": 416,
        "y": 577,
        "w": 32,
        "h": 23
      },
      "o": {
        "x": 0,
        "y": 582,
        "w": 39,
        "h": 68
      }
    },
    "40:4:4": {
      "h": {
        "x": 318,
        "y": 582,
        "w": 98,
        "h": 68
      },
      "p": {
        "x": 318,
        "y": 577,
        "w": 98,
        "h": 23
      },
      "o": {
        "x": 0,
        "y": 582,
        "w": 39,
        "h": 68
      }
    },
    "40:4:5": {
      "h": {
        "x": 249,
        "y": 582,
        "w": 69,
        "h": 68
      },
      "p": {
        "x": 249,
        "y": 577,
        "w": 69,
        "h": 23
      },
      "o": {
        "x": 0,
        "y": 582,
        "w": 39,
        "h": 68
      }
    },
    "40:4:6": {
      "h": {
        "x": 193,
        "y": 582,
        "w": 56,
        "h": 68
      },
      "p": {
        "x": 193,
        "y": 577,
        "w": 56,
        "h": 23
      },
      "o": {
        "x": 0,
        "y": 582,
        "w": 39,
        "h": 68
      }
    },
    "40:4:7": {
      "h": {
        "x": 123,
        "y": 582,
        "w": 70,
        "h": 68
      },
      "p": {
        "x": 123,
        "y": 577,
        "w": 70,
        "h": 23
      },
      "o": {
        "x": 0,
        "y": 582,
        "w": 39,
        "h": 68
      }
    },
    "40:4:8": {
      "h": {
        "x": 40,
        "y": 582,
        "w": 83,
        "h": 68
      },
      "p": {
        "x": 40,
        "y": 577,
        "w": 83,
        "h": 23
      },
      "o": {
        "x": 0,
        "y": 582,
        "w": 39,
        "h": 68
      }
    },
    "40:4:9": {
      "h": {
        "x": 827,
        "y": 676,
        "w": 49,
        "h": 68
      },
      "p": {
        "x": 827,
        "y": 671,
        "w": 49,
        "h": 23
      },
      "o": {
        "x": 0,
        "y": 676,
        "w": 39,
        "h": 68
      }
    },
    "40:4:10": {
      "h": {
        "x": 722,
        "y": 676,
        "w": 105,
        "h": 68
      },
      "p": {
        "x": 722,
        "y": 671,
        "w": 105,
        "h": 23
      },
      "o": {
        "x": 0,
        "y": 676,
        "w": 39,
        "h": 68
      }
    },
    "40:4:11": {
      "h": {
        "x": 619,
        "y": 676,
        "w": 103,
        "h": 68
      },
      "p": {
        "x": 619,
        "y": 671,
        "w": 103,
        "h": 23
      },
      "o": {
        "x": 0,
        "y": 676,
        "w": 39,
        "h": 68
      }
    },
    "40:4:12": {
      "h": {
        "x": 579,
        "y": 676,
        "w": 40,
        "h": 68
      },
      "p": {
        "x": 579,
        "y": 671,
        "w": 40,
        "h": 23
      },
      "o": {
        "x": 0,
        "y": 676,
        "w": 39,
        "h": 68
      }
    },
    "40:4:13": {
      "h": {
        "x": 470,
        "y": 676,
        "w": 109,
        "h": 68
      },
      "p": {
        "x": 470,
        "y": 671,
        "w": 109,
        "h": 23
      },
      "o": {
        "x": 0,
        "y": 676,
        "w": 39,
        "h": 68
      }
    },
    "40:5:1": {
      "h": {
        "x": 214,
        "y": 676,
        "w": 181,
        "h": 68
      },
      "p": {
        "x": 214,
        "y": 671,
        "w": 181,
        "h": 23
      },
      "o": {
        "x": 0,
        "y": 676,
        "w": 39,
        "h": 68
      }
    },
    "40:5:2": {
      "h": {
        "x": 94,
        "y": 676,
        "w": 120,
        "h": 68
      },
      "p": {
        "x": 94,
        "y": 671,
        "w": 120,
        "h": 23
      },
      "o": {
        "x": 0,
        "y": 676,
        "w": 39,
        "h": 68
      }
    },
    "40:5:3": {
      "h": {
        "x": 40,
        "y": 676,
        "w": 54,
        "h": 68
      },
      "p": {
        "x": 40,
        "y": 671,
        "w": 54,
        "h": 23
      },
      "o": {
        "x": 0,
        "y": 676,
        "w": 39,
        "h": 68
      }
    },
    "40:5:4": {
      "h": {
        "x": 811,
        "y": 770,
        "w": 65,
        "h": 68
      },
      "p": {
        "x": 811,
        "y": 765,
        "w": 65,
        "h": 23
      },
      "o": {
        "x": 0,
        "y": 770,
        "w": 39,
        "h": 68
      }
    },
    "40:5:5": {
      "h": {
        "x": 632,
        "y": 770,
        "w": 179,
        "h": 68
      },
      "p": {
        "x": 632,
        "y": 765,
        "w": 179,
        "h": 23
      },
      "o": {
        "x": 0,
        "y": 770,
        "w": 39,
        "h": 68
      }
    },
    "40:5:6": {
      "h": {
        "x": 577,
        "y": 770,
        "w": 55,
        "h": 68
      },
      "p": {
        "x": 577,
        "y": 765,
        "w": 55,
        "h": 23
      },
      "o": {
        "x": 0,
        "y": 770,
        "w": 39,
        "h": 68
      }
    },
    "40:5:7": {
      "h": {
        "x": 458,
        "y": 770,
        "w": 119,
        "h": 68
      },
      "p": {
        "x": 458,
        "y": 765,
        "w": 119,
        "h": 23
      },
      "o": {
        "x": 0,
        "y": 770,
        "w": 39,
        "h": 68
      }
    },
    "40:5:9": {
      "h": {
        "x": 329,
        "y": 770,
        "w": 128,
        "h": 68
      },
      "p": {
        "x": 329,
        "y": 765,
        "w": 128,
        "h": 23
      },
      "o": {
        "x": 0,
        "y": 770,
        "w": 39,
        "h": 68
      }
    },
    "40:5:10": {
      "h": {
        "x": 202,
        "y": 770,
        "w": 127,
        "h": 68
      },
      "p": {
        "x": 202,
        "y": 765,
        "w": 127,
        "h": 23
      },
      "o": {
        "x": 0,
        "y": 770,
        "w": 39,
        "h": 68
      }
    },
    "40:5:11": {
      "h": {
        "x": 146,
        "y": 770,
        "w": 56,
        "h": 68
      },
      "p": {
        "x": 146,
        "y": 765,
        "w": 56,
        "h": 23
      },
      "o": {
        "x": 0,
        "y": 770,
        "w": 39,
        "h": 68
      }
    },
    "40:5:12": {
      "h": {
        "x": 40,
        "y": 770,
        "w": 106,
        "h": 68
      },
      "p": {
        "x": 40,
        "y": 765,
        "w": 106,
        "h": 23
      },
      "o": {
        "x": 0,
        "y": 770,
        "w": 39,
        "h": 68
      }
    },
    "40:5:13": {
      "h": {
        "x": 732,
        "y": 864,
        "w": 147,
        "h": 68
      },
      "p": {
        "x": 732,
        "y": 859,
        "w": 147,
        "h": 23
      },
      "o": {
        "x": 0,
        "y": 864,
        "w": 39,
        "h": 68
      }
    },
    "40:5:15": {
      "h": {
        "x": 587,
        "y": 864,
        "w": 144,
        "h": 68
      },
      "p": {
        "x": 587,
        "y": 859,
        "w": 144,
        "h": 23
      },
      "o": {
        "x": 0,
        "y": 864,
        "w": 39,
        "h": 68
      }
    },
    "40:5:16": {
      "h": {
        "x": 450,
        "y": 864,
        "w": 137,
        "h": 68
      },
      "p": {
        "x": 450,
        "y": 859,
        "w": 137,
        "h": 23
      },
      "o": {
        "x": 0,
        "y": 864,
        "w": 39,
        "h": 68
      }
    },
    "40:5:17": {
      "h": {
        "x": 272,
        "y": 864,
        "w": 178,
        "h": 68
      },
      "p": {
        "x": 272,
        "y": 859,
        "w": 178,
        "h": 23
      },
      "o": {
        "x": 0,
        "y": 864,
        "w": 39,
        "h": 68
      }
    },
    "40:5:18": {
      "h": {
        "x": 234,
        "y": 864,
        "w": 38,
        "h": 68
      },
      "p": {
        "x": 234,
        "y": 859,
        "w": 38,
        "h": 23
      },
      "o": {
        "x": 0,
        "y": 864,
        "w": 39,
        "h": 68
      }
    },
    "40:5:19": {
      "h": {
        "x": 151,
        "y": 864,
        "w": 83,
        "h": 68
      },
      "p": {
        "x": 151,
        "y": 859,
        "w": 83,
        "h": 23
      },
      "o": {
        "x": 0,
        "y": 864,
        "w": 39,
        "h": 68
      }
    },
    "40:5:20": {
      "h": {
        "x": 43,
        "y": 864,
        "w": 108,
        "h": 68
      },
      "p": {
        "x": 43,
        "y": 859,
        "w": 108,
        "h": 23
      },
      "o": {
        "x": 0,
        "y": 864,
        "w": 39,
        "h": 68
      }
    },
    "40:5:22": {
      "h": {
        "x": 748,
        "y": 958,
        "w": 131,
        "h": 68
      },
      "p": {
        "x": 748,
        "y": 953,
        "w": 131,
        "h": 23
      },
      "o": {
        "x": 0,
        "y": 958,
        "w": 39,
        "h": 68
      }
    },
    "40:5:23": {
      "h": {
        "x": 718,
        "y": 958,
        "w": 30,
        "h": 68
      },
      "p": {
        "x": 718,
        "y": 953,
        "w": 30,
        "h": 23
      },
      "o": {
        "x": 0,
        "y": 958,
        "w": 39,
        "h": 68
      }
    },
    "40:5:24": {
      "h": {
        "x": 605,
        "y": 958,
        "w": 113,
        "h": 68
      },
      "p": {
        "x": 605,
        "y": 953,
        "w": 113,
        "h": 23
      },
      "o": {
        "x": 0,
        "y": 958,
        "w": 39,
        "h": 68
      }
    },
    "40:6:1": {
      "h": {
        "x": 403,
        "y": 958,
        "w": 128,
        "h": 68
      },
      "p": {
        "x": 403,
        "y": 953,
        "w": 128,
        "h": 23
      },
      "o": {
        "x": 0,
        "y": 958,
        "w": 39,
        "h": 68
      }
    },
    "40:6:2": {
      "h": {
        "x": 299,
        "y": 958,
        "w": 104,
        "h": 68
      },
      "p": {
        "x": 299,
        "y": 953,
        "w": 104,
        "h": 23
      },
      "o": {
        "x": 0,
        "y": 958,
        "w": 39,
        "h": 68
      }
    },
    "40:6:3": {
      "h": {
        "x": 202,
        "y": 958,
        "w": 97,
        "h": 68
      },
      "p": {
        "x": 202,
        "y": 953,
        "w": 97,
        "h": 23
      },
      "o": {
        "x": 0,
        "y": 958,
        "w": 39,
        "h": 68
      }
    },
    "40:6:4": {
      "h": {
        "x": 76,
        "y": 958,
        "w": 126,
        "h": 68
      },
      "p": {
        "x": 76,
        "y": 953,
        "w": 126,
        "h": 23
      },
      "o": {
        "x": 0,
        "y": 958,
        "w": 39,
        "h": 68
      }
    },
    "40:6:5": {
      "h": {
        "x": 40,
        "y": 958,
        "w": 36,
        "h": 68
      },
      "p": {
        "x": 40,
        "y": 953,
        "w": 36,
        "h": 23
      },
      "o": {
        "x": 0,
        "y": 958,
        "w": 39,
        "h": 68
      }
    },
    "40:6:6": {
      "h": {
        "x": 791,
        "y": 1052,
        "w": 88,
        "h": 68
      },
      "p": {
        "x": 791,
        "y": 1047,
        "w": 88,
        "h": 23
      },
      "o": {
        "x": 0,
        "y": 1052,
        "w": 39,
        "h": 68
      }
    },
    "40:6:7": {
      "h": {
        "x": 684,
        "y": 1052,
        "w": 107,
        "h": 68
      },
      "p": {
        "x": 684,
        "y": 1047,
        "w": 107,
        "h": 23
      },
      "o": {
        "x": 0,
        "y": 1052,
        "w": 39,
        "h": 68
      }
    },
    "40:6:8": {
      "h": {
        "x": 602,
        "y": 1052,
        "w": 82,
        "h": 68
      },
      "p": {
        "x": 602,
        "y": 1047,
        "w": 82,
        "h": 23
      },
      "o": {
        "x": 0,
        "y": 1052,
        "w": 39,
        "h": 68
      }
    },
    "40:6:9": {
      "h": {
        "x": 453,
        "y": 1052,
        "w": 149,
        "h": 68
      },
      "p": {
        "x": 453,
        "y": 1047,
        "w": 149,
        "h": 23
      },
      "o": {
        "x": 0,
        "y": 1052,
        "w": 39,
        "h": 68
      }
    },
    "40:6:10": {
      "h": {
        "x": 368,
        "y": 1052,
        "w": 85,
        "h": 68
      },
      "p": {
        "x": 368,
        "y": 1047,
        "w": 85,
        "h": 23
      },
      "o": {
        "x": 0,
        "y": 1052,
        "w": 39,
        "h": 68
      }
    },
    "40:7:1": {
      "h": {
        "x": 233,
        "y": 1052,
        "w": 70,
        "h": 68
      },
      "p": {
        "x": 233,
        "y": 1047,
        "w": 70,
        "h": 23
      },
      "o": {
        "x": 0,
        "y": 1052,
        "w": 39,
        "h": 68
      }
    },
    "40:7:2": {
      "h": {
        "x": 118,
        "y": 1052,
        "w": 115,
        "h": 68
      },
      "p": {
        "x": 118,
        "y": 1047,
        "w": 115,
        "h": 23
      },
      "o": {
        "x": 0,
        "y": 1052,
        "w": 39,
        "h": 68
      }
    },
    "40:7:3": {
      "h": {
        "x": 40,
        "y": 1052,
        "w": 78,
        "h": 68
      },
      "p": {
        "x": 40,
        "y": 1047,
        "w": 78,
        "h": 23
      },
      "o": {
        "x": 0,
        "y": 1052,
        "w": 39,
        "h": 68
      }
    },
    "40:7:4": {
      "h": {
        "x": 814,
        "y": 1147,
        "w": 65,
        "h": 68
      },
      "p": {
        "x": 814,
        "y": 1142,
        "w": 65,
        "h": 23
      },
      "o": {
        "x": 0,
        "y": 1147,
        "w": 39,
        "h": 68
      }
    },
    "40:7:5": {
      "h": {
        "x": 723,
        "y": 1147,
        "w": 91,
        "h": 68
      },
      "p": {
        "x": 723,
        "y": 1142,
        "w": 91,
        "h": 23
      },
      "o": {
        "x": 0,
        "y": 1147,
        "w": 39,
        "h": 68
      }
    },
    "40:7:6": {
      "h": {
        "x": 579,
        "y": 1147,
        "w": 144,
        "h": 68
      },
      "p": {
        "x": 579,
        "y": 1142,
        "w": 144,
        "h": 23
      },
      "o": {
        "x": 0,
        "y": 1147,
        "w": 39,
        "h": 68
      }
    },
    "40:7:7": {
      "h": {
        "x": 484,
        "y": 1147,
        "w": 95,
        "h": 68
      },
      "p": {
        "x": 484,
        "y": 1142,
        "w": 95,
        "h": 23
      },
      "o": {
        "x": 0,
        "y": 1147,
        "w": 39,
        "h": 68
      }
    },
    "40:7:8": {
      "h": {
        "x": 395,
        "y": 1147,
        "w": 89,
        "h": 68
      },
      "p": {
        "x": 395,
        "y": 1142,
        "w": 89,
        "h": 23
      },
      "o": {
        "x": 0,
        "y": 1147,
        "w": 39,
        "h": 68
      }
    },
    "40:7:9": {
      "h": {
        "x": 262,
        "y": 1147,
        "w": 133,
        "h": 68
      },
      "p": {
        "x": 262,
        "y": 1142,
        "w": 133,
        "h": 23
      },
      "o": {
        "x": 0,
        "y": 1147,
        "w": 39,
        "h": 68
      }
    },
    "40:7:10": {
      "h": {
        "x": 191,
        "y": 1147,
        "w": 71,
        "h": 68
      },
      "p": {
        "x": 191,
        "y": 1142,
        "w": 71,
        "h": 23
      },
      "o": {
        "x": 0,
        "y": 1147,
        "w": 39,
        "h": 68
      }
    },
    "40:7:11": {
      "h": {
        "x": 40,
        "y": 1147,
        "w": 151,
        "h": 68
      },
      "p": {
        "x": 40,
        "y": 1142,
        "w": 151,
        "h": 23
      },
      "o": {
        "x": 0,
        "y": 1147,
        "w": 39,
        "h": 68
      }
    },
    "40:7:12": {
      "h": {
        "x": 788,
        "y": 1240,
        "w": 91,
        "h": 68
      },
      "p": {
        "x": 788,
        "y": 1235,
        "w": 91,
        "h": 23
      },
      "o": {
        "x": 0,
        "y": 1240,
        "w": 39,
        "h": 68
      }
    },
    "40:7:13": {
      "h": {
        "x": 680,
        "y": 1240,
        "w": 108,
        "h": 68
      },
      "p": {
        "x": 680,
        "y": 1235,
        "w": 108,
        "h": 23
      },
      "o": {
        "x": 0,
        "y": 1240,
        "w": 39,
        "h": 68
      }
    },
    "40:7:14": {
      "h": {
        "x": 610,
        "y": 1240,
        "w": 70,
        "h": 68
      },
      "p": {
        "x": 610,
        "y": 1235,
        "w": 70,
        "h": 23
      },
      "o": {
        "x": 0,
        "y": 1240,
        "w": 39,
        "h": 68
      }
    },
    "40:7:15": {
      "h": {
        "x": 475,
        "y": 1240,
        "w": 135,
        "h": 68
      },
      "p": {
        "x": 475,
        "y": 1235,
        "w": 135,
        "h": 23
      },
      "o": {
        "x": 0,
        "y": 1240,
        "w": 39,
        "h": 68
      }
    },
    "40:7:16": {
      "h": {
        "x": 347,
        "y": 1240,
        "w": 128,
        "h": 68
      },
      "p": {
        "x": 347,
        "y": 1235,
        "w": 128,
        "h": 23
      },
      "o": {
        "x": 0,
        "y": 1240,
        "w": 39,
        "h": 68
      }
    },
    "40:7:17": {
      "h": {
        "x": 258,
        "y": 1240,
        "w": 89,
        "h": 68
      },
      "p": {
        "x": 258,
        "y": 1235,
        "w": 89,
        "h": 23
      },
      "o": {
        "x": 0,
        "y": 1240,
        "w": 39,
        "h": 68
      }
    },
    "40:7:18": {
      "h": {
        "x": 128,
        "y": 1240,
        "w": 130,
        "h": 68
      },
      "p": {
        "x": 128,
        "y": 1235,
        "w": 130,
        "h": 23
      },
      "o": {
        "x": 0,
        "y": 1240,
        "w": 39,
        "h": 68
      }
    },
    "40:7:19": {
      "h": {
        "x": 40,
        "y": 1240,
        "w": 88,
        "h": 68
      },
      "p": {
        "x": 40,
        "y": 1235,
        "w": 88,
        "h": 23
      },
      "o": {
        "x": 0,
        "y": 1240,
        "w": 39,
        "h": 68
      }
    },
    "40:7:20": {
      "h": {
        "x": 776,
        "y": 1334,
        "w": 103,
        "h": 68
      },
      "p": {
        "x": 776,
        "y": 1329,
        "w": 103,
        "h": 23
      },
      "o": {
        "x": 0,
        "y": 1334,
        "w": 39,
        "h": 68
      }
    },
    "40:7:21": {
      "h": {
        "x": 678,
        "y": 1334,
        "w": 98,
        "h": 68
      },
      "p": {
        "x": 678,
        "y": 1329,
        "w": 98,
        "h": 23
      },
      "o": {
        "x": 0,
        "y": 1334,
        "w": 39,
        "h": 68
      }
    },
    "40:7:22": {
      "h": {
        "x": 601,
        "y": 1334,
        "w": 77,
        "h": 68
      },
      "p": {
        "x": 601,
        "y": 1329,
        "w": 77,
        "h": 23
      },
      "o": {
        "x": 0,
        "y": 1334,
        "w": 39,
        "h": 68
      }
    },
    "40:7:23": {
      "h": {
        "x": 471,
        "y": 1334,
        "w": 130,
        "h": 68
      },
      "p": {
        "x": 471,
        "y": 1329,
        "w": 130,
        "h": 23
      },
      "o": {
        "x": 0,
        "y": 1334,
        "w": 39,
        "h": 68
      }
    },
    "40:7:24": {
      "h": {
        "x": 352,
        "y": 1334,
        "w": 119,
        "h": 68
      },
      "p": {
        "x": 352,
        "y": 1329,
        "w": 119,
        "h": 23
      },
      "o": {
        "x": 0,
        "y": 1334,
        "w": 39,
        "h": 68
      }
    },
    "40:7:25": {
      "h": {
        "x": 286,
        "y": 1334,
        "w": 66,
        "h": 68
      },
      "p": {
        "x": 286,
        "y": 1329,
        "w": 66,
        "h": 23
      },
      "o": {
        "x": 0,
        "y": 1334,
        "w": 39,
        "h": 68
      }
    },
    "40:7:26": {
      "h": {
        "x": 211,
        "y": 1334,
        "w": 75,
        "h": 68
      },
      "p": {
        "x": 211,
        "y": 1329,
        "w": 75,
        "h": 23
      },
      "o": {
        "x": 0,
        "y": 1334,
        "w": 39,
        "h": 68
      }
    },
    "40:7:27": {
      "h": {
        "x": 88,
        "y": 1334,
        "w": 123,
        "h": 68
      },
      "p": {
        "x": 88,
        "y": 1329,
        "w": 123,
        "h": 23
      },
      "o": {
        "x": 0,
        "y": 1334,
        "w": 39,
        "h": 68
      }
    }
  }
}